my_first_python_package/__init__.py
my_first_python_package/module1.py
my_first_python_package_0-1.1.1.dist-info/LICENSE
my_first_python_package_0-1.1.1.dist-info/METADATA
my_first_python_package_0-1.1.1.dist-info/WHEEL
my_first_python_package_0-1.1.1.dist-info/RECORD
