Metadata-Version: 2.1
Name: my-first-python-package-0
Version: 1.1.1
Summary: A simple package to demonstrate how to create a python package
License: BSD-3-Clause
Author: Hassan Abedi
Author-email: hassan.abedi.t@gmail.com
Requires-Python: >=3.9,<4.0
Classifier: License :: OSI Approved :: BSD License
Classifier: Programming Language :: Python :: 3
Classifier: Programming Language :: Python :: 3.9
Classifier: Programming Language :: Python :: 3.10
Classifier: Programming Language :: Python :: 3.11
Classifier: Programming Language :: Python :: 3.12
Requires-Dist: pytest (>=8.1.1,<9.0.0)
Requires-Dist: trove-classifiers (>=2024.3.25,<2025.0.0)
